cjm_fasthtml_sysmon/__init__.py
cjm_fasthtml_sysmon/_modidx.py
cjm_fasthtml_sysmon/components/__init__.py
cjm_fasthtml_sysmon/components/base.py
cjm_fasthtml_sysmon/components/cards.py
cjm_fasthtml_sysmon/components/common.py
cjm_fasthtml_sysmon/components/modals.py
cjm_fasthtml_sysmon/components/tables.py
cjm_fasthtml_sysmon/core/__init__.py
cjm_fasthtml_sysmon/core/html_ids.py
cjm_fasthtml_sysmon/core/utils.py
cjm_fasthtml_sysmon/monitors/__init__.py
cjm_fasthtml_sysmon/monitors/cpu.py
cjm_fasthtml_sysmon/monitors/disk.py
cjm_fasthtml_sysmon/monitors/gpu.py
cjm_fasthtml_sysmon/monitors/memory.py
cjm_fasthtml_sysmon/monitors/network.py
cjm_fasthtml_sysmon/monitors/processes.py
cjm_fasthtml_sysmon/monitors/sensors.py
cjm_fasthtml_sysmon/monitors/system.py
cjm_fasthtml_sysmon-0.0.13.dist-info/licenses/LICENSE
cjm_fasthtml_sysmon-0.0.13.dist-info/METADATA
cjm_fasthtml_sysmon-0.0.13.dist-info/WHEEL
cjm_fasthtml_sysmon-0.0.13.dist-info/entry_points.txt
cjm_fasthtml_sysmon-0.0.13.dist-info/top_level.txt
cjm_fasthtml_sysmon-0.0.13.dist-info/RECORD
